anmetal/__init__.py
anmetal/cli.py
anmetal/commands/__init__.py
anmetal/commands/basic_math_it_optimization.py
anmetal/commands/basic_mh_optimization_npcomp.py
anmetal/commands/categorical_mh_optimization.py
anmetal/commands/genetic_categorical_plot.py
anmetal/commands/mh_graph_each_it.py
anmetal/commands/nonlinear_mh_optimization.py
anmetal/commands/trajectory_plot_npcomp.py
anmetal/optimizer/__init__.py
anmetal/optimizer/population/IMetaheuristic.py
anmetal/optimizer/population/ISolution.py
anmetal/optimizer/population/__init__.py
anmetal/optimizer/population/ABC/__init__.py
anmetal/optimizer/population/ABC/abc.py
anmetal/optimizer/population/ACO/__init__.py
anmetal/optimizer/population/ACO/aco.py
anmetal/optimizer/population/AFSA/AFSAMH_Real.py
anmetal/optimizer/population/AFSA/__init__.py
anmetal/optimizer/population/Bat/__init__.py
anmetal/optimizer/population/Bat/bat.py
anmetal/optimizer/population/Blackhole/__init__.py
anmetal/optimizer/population/Blackhole/blackhole.py
anmetal/optimizer/population/Cuckoo/__init__.py
anmetal/optimizer/population/Cuckoo/cuckoo.py
anmetal/optimizer/population/Firefly/__init__.py
anmetal/optimizer/population/Firefly/firefly.py
anmetal/optimizer/population/Genetic/GeneticMH_Categorical.py
anmetal/optimizer/population/Genetic/GeneticMH_Categorical_WithLeap.py
anmetal/optimizer/population/Genetic/__init__.py
anmetal/optimizer/population/Greedy/GreedyMH_Real.py
anmetal/optimizer/population/Greedy/GreedyMH_Real_WithLeap.py
anmetal/optimizer/population/Greedy/__init__.py
anmetal/optimizer/population/Harmony/__init__.py
anmetal/optimizer/population/Harmony/harmony.py
anmetal/optimizer/population/PSO/PSOMH_Real.py
anmetal/optimizer/population/PSO/PSOMH_Real_WithLeap.py
anmetal/optimizer/population/PSO/Particle.py
anmetal/optimizer/population/PSO/__init__.py
anmetal/optimizer/single_solution/__init__.py
anmetal/optimizer/single_solution/iterative_methods.py
anmetal/problems/IProblem.py
anmetal/problems/__init__.py
anmetal-1.0.0.dist-info/METADATA
anmetal-1.0.0.dist-info/WHEEL
anmetal-1.0.0.dist-info/entry_points.txt
anmetal-1.0.0.dist-info/licenses/LICENSE
anmetal-1.0.0.dist-info/RECORD
