Metadata-Version: 2.4
Name: anmetal
Version: 1.0.0
Summary: Another Numeric optimization and Metaheuristics Library
Project-URL: Homepage, https://github.com/erickfmm/ANMetaL
Project-URL: Bug Tracker, https://github.com/erickfmm/ANMetaL/issues
Author-email: Erick Merino <erickfmm@gmail.com>
Maintainer-email: Erick Merino <erickfmm@gmail.com>
License: MIT License
License-File: LICENSE
Keywords: metaheuristic,optimization
Classifier: License :: OSI Approved :: MIT License
Classifier: Operating System :: OS Independent
Classifier: Programming Language :: Python :: 3
Requires-Python: >=3.9
Requires-Dist: matplotlib>=3.5.0
Requires-Dist: numpy>=1.21.0
Requires-Dist: opencv-python>=4.5.0
Requires-Dist: pandas>=1.3.0
Requires-Dist: seaborn>=0.12.0
Provides-Extra: test
Requires-Dist: matplotlib; extra == 'test'
Requires-Dist: pandas; extra == 'test'
Requires-Dist: seaborn; extra == 'test'
